LICENSE
geojsonhash/__init__.py
geojsonhash/geojsonhash.py
geojsonhash-0.1.1.dist-info/LICENSE
geojsonhash-0.1.1.dist-info/WHEEL
geojsonhash-0.1.1.dist-info/METADATA
geojsonhash-0.1.1.dist-info/RECORD
