Metadata-Version: 2.1
Name: geojsonhash
Version: 0.1.1
Summary: README
Home-page: https://github.com/AdrianSeguraOrtiz/geojsonhash/
Author: Adrián Segura Ortiz
Author-email: adrianseor.99@gmail.com
Requires-Python: >=3.9,<4.0
Classifier: Intended Audience :: Science/Research
Classifier: License :: OSI Approved :: MIT License
Classifier: Operating System :: OS Independent
Classifier: Programming Language :: Python
Classifier: Programming Language :: Python :: 3
Classifier: Programming Language :: Python :: 3.9
Classifier: Typing :: Typed
Requires-Dist: pygeohash (>=1.2.0)
Project-URL: Repository, https://github.com/AdrianSeguraOrtiz/geojsonhash/
